LICENSE
README.md
webhook_manager/__init__.py
webhook_manager/__main__.py
webhook_manager/cli.py
webhook_manager/client.py
webhook_manager/models.py
circleci_webhook_manager-0.0.3.dist-info/LICENSE
circleci_webhook_manager-0.0.3.dist-info/METADATA
circleci_webhook_manager-0.0.3.dist-info/WHEEL
circleci_webhook_manager-0.0.3.dist-info/entry_points.txt
circleci_webhook_manager-0.0.3.dist-info/RECORD
