Metadata-Version: 2.1
Name: circleci-webhook-manager
Version: 0.0.3
Summary: This project aims to provide a simple way to manage bulk (selective or organization-wide) CircleCI webhooks.
License: MIT
Keywords: cli,circleci,webhook,manager,webhook,organization
Author: Mark Beacom
Author-email: m@beacom.dev
Requires-Python: >=3.8,<4.0
Classifier: License :: OSI Approved :: MIT License
Classifier: Programming Language :: Python
Classifier: Programming Language :: Python :: 3
Classifier: Programming Language :: Python :: 3.8
Classifier: Programming Language :: Python :: 3.9
Classifier: Programming Language :: Python :: 3.10
Classifier: Programming Language :: Python :: 3.11
Requires-Dist: httpx (>=0.24.1,<0.25.0)
Requires-Dist: typer[all] (>=0.9.0,<0.10.0)
